pytegrity/__init__.py
pytegrity/tubular_integrity.py
pytegrity-0.1.6.3.dist-info/METADATA
pytegrity-0.1.6.3.dist-info/WHEEL
pytegrity-0.1.6.3.dist-info/top_level.txt
pytegrity-0.1.6.3.dist-info/RECORD
