Metadata-Version: 2.1
Name: pytegrity
Version: 0.1.6.3
Summary: Well Integrity Log analysis and Visualization tool [This is a Test Release]
Home-page: https://github.com/Nashat90/pytegrity
Author: Nashat Jumaah Omar
Author-email: nashattt90@gmail.com
Classifier: Programming Language :: Python :: 3
Classifier: License :: OSI Approved :: MIT License
Classifier: Operating System :: OS Independent
Requires-Dist: numpy
Requires-Dist: pandas
Requires-Dist: pyvista
Requires-Dist: trame
Requires-Dist: pyvista[trame]
